{"metadata":{"dist-tags":{"latest":"4.2.0"},"versions":{"3.1.2":{"name":"crypto-js","dist":{"tarball":"https://registry.npmjs.org/crypto-js/-/crypto-js-3.1.2.tgz"},"scripts":{},"dependencies":{}},"3.1.2-1":{"name":"crypto-js","dist":{"tarball":"https://registry.npmjs.org/crypto-js/-/crypto-js-3.1.2-1.tgz"},"scripts":{},"dependencies":{}},"3.1.2-2":{"name":"crypto-js","dist":{"tarball":"https://registry.npmjs.org/crypto-js/-/crypto-js-3.1.2-2.tgz"},"scripts":{},"dependencies":{}},"3.1.2-3":{"name":"crypto-js","dist":{"tarball":"https://registry.npmjs.org/crypto-js/-/crypto-js-3.1.2-3.tgz"},"scripts":{},"dependencies":{}},"3.1.2-4":{"name":"crypto-js","dist":{"tarball":"https://registry.npmjs.org/crypto-js/-/crypto-js-3.1.2-4.tgz"},"scripts":{},"dependencies":{}},"3.1.2-5":{"name":"crypto-js","dist":{"tarball":"https://registry.npmjs.org/crypto-js/-/crypto-js-3.1.2-5.tgz"},"scripts":{},"dependencies":{}},"3.1.2-6":{"name":"crypto-js","dist":{"tarball":"https://registry.npmjs.org/crypto-js/-/crypto-js-3.1.2-6.tgz"},"scripts":{},"dependencies":{}},"3.1.4":{"name":"crypto-js","dist":{"tarball":"https://registry.npmjs.org/crypto-js/-/crypto-js-3.1.4.tgz"},"scripts":{},"dependencies":{}},"3.1.5":{"name":"crypto-js","dist":{"tarball":"https://registry.npmjs.org/crypto-js/-/crypto-js-3.1.5.tgz"},"scripts":{},"dependencies":{}},"3.1.6":{"name":"crypto-js","dist":{"tarball":"https://registry.npmjs.org/crypto-js/-/crypto-js-3.1.6.tgz"},"scripts":{},"dependencies":{}},"3.1.7":{"name":"crypto-js","dist":{"tarball":"https://registry.npmjs.org/crypto-js/-/crypto-js-3.1.7.tgz"},"scripts":{},"dependencies":{}},"3.1.8":{"name":"crypto-js","dist":{"tarball":"https://registry.npmjs.org/crypto-js/-/crypto-js-3.1.8.tgz"},"scripts":{},"dependencies":{}},"3.1.9-1":{"name":"crypto-js","dist":{"tarball":"https://registry.npmjs.org/crypto-js/-/crypto-js-3.1.9-1.tgz"},"scripts":{},"dependencies":{}},"3.2.0":{"name":"crypto-js","dist":{"tarball":"https://registry.npmjs.org/crypto-js/-/crypto-js-3.2.0.tgz"},"scripts":{},"dependencies":{},"deprecated":"Critical"},"3.2.1":{"name":"crypto-js","dist":{"tarball":"https://registry.npmjs.org/crypto-js/-/crypto-js-3.2.1.tgz"},"scripts":{},"dependencies":{}},"3.3.0":{"name":"crypto-js","dist":{"tarball":"https://registry.npmjs.org/crypto-js/-/crypto-js-3.3.0.tgz"},"scripts":{},"dependencies":{}},"4.0.0":{"name":"crypto-js","dist":{"tarball":"https://registry.npmjs.org/crypto-js/-/crypto-js-4.0.0.tgz"},"scripts":{},"dependencies":{}},"4.1.0":{"name":"crypto-js","dist":{"tarball":"https://registry.npmjs.org/crypto-js/-/crypto-js-4.1.0.tgz"},"dependencies":{}},"4.1.1":{"name":"crypto-js","dist":{"tarball":"https://registry.npmjs.org/crypto-js/-/crypto-js-4.1.1.tgz"},"dependencies":{}},"4.2.0":{"name":"crypto-js","dist":{"tarball":"https://registry.npmjs.org/crypto-js/-/crypto-js-4.2.0.tgz"},"dependencies":{}}}},"etag":"W/\"ef406c7d2edee1b84c35e6bd9defb27f\"","lastModified":"Mon, 01 Jul 2024 21:09:34 GMT"}
