{"metadata":{"dist-tags":{"latest":"8.0.4"},"versions":{"0.0.1":{"name":"is-ipfs","dist":{"tarball":"https://registry.npmjs.org/is-ipfs/-/is-ipfs-0.0.1.tgz"},"scripts":{"test":"tape test.js","lint":"standard"},"dependencies":{"bs58":"^3.0.0","multihashes":"^0.2.0"}},"0.0.2":{"name":"is-ipfs","dist":{"tarball":"https://registry.npmjs.org/is-ipfs/-/is-ipfs-0.0.2.tgz"},"scripts":{"test":"tape test.js","lint":"standard"},"dependencies":{"bs58":"^3.0.0","multihashes":"^0.2.0"}},"0.0.4":{"name":"is-ipfs","dist":{"tarball":"https://registry.npmjs.org/is-ipfs/-/is-ipfs-0.0.4.tgz"},"scripts":{"test":"tape test.js","lint":"standard"},"dependencies":{"bs58":"^3.0.0","multihashes":"^0.2.0"}},"0.1.0":{"name":"is-ipfs","dist":{"tarball":"https://registry.npmjs.org/is-ipfs/-/is-ipfs-0.1.0.tgz"},"scripts":{"test":"tape test-*.js","lint":"standard"},"dependencies":{"bs58":"^3.0.0","multihashes":"^0.2.0"}},"0.2.0":{"name":"is-ipfs","dist":{"tarball":"https://registry.npmjs.org/is-ipfs/-/is-ipfs-0.2.0.tgz"},"scripts":{"test:node":"dignified-test node","test:browser":"dignified-test browser","test":"dignified-test","lint":"dignified-lint","release":"dignified-release","build":"dignified-build"},"dependencies":{"bs58":"^3.0.0","multihashes":"^0.2.0"}},"0.2.1":{"name":"is-ipfs","dist":{"tarball":"https://registry.npmjs.org/is-ipfs/-/is-ipfs-0.2.1.tgz"},"scripts":{"test:node":"aegir-test node","test:browser":"aegir-test browser","test":"aegir-test","lint":"aegir-lint","release":"aegir-release","build":"aegir-build","coverage":"aegir-coverage","coverage-publish":"aegir-coverage publish"},"dependencies":{"bs58":"^3.0.0","multihashes":"^0.2.0"}},"0.3.0":{"name":"is-ipfs","dist":{"tarball":"https://registry.npmjs.org/is-ipfs/-/is-ipfs-0.3.0.tgz"},"scripts":{"test:node":"aegir-test node","test:browser":"aegir-test browser","test":"aegir-test","lint":"aegir-lint","release":"aegir-release","release-minor":"aegir-release --type minor","release-major":"aegir-release --type major","build":"aegir-build","coverage":"aegir-coverage","coverage-publish":"aegir-coverage publish"},"dependencies":{"bs58":"^4.0.0","multihashes":"^0.3.2"}},"0.3.2":{"name":"is-ipfs","dist":{"tarball":"https://registry.npmjs.org/is-ipfs/-/is-ipfs-0.3.2.tgz"},"scripts":{"test:node":"aegir-test node","test:browser":"aegir-test browser","test":"aegir-test","lint":"aegir-lint","release":"aegir-release","release-minor":"aegir-release --type minor","release-major":"aegir-release --type major","build":"aegir-build","coverage":"aegir-coverage","coverage-publish":"aegir-coverage publish"},"dependencies":{"cids":"~0.5.1","bs58":"^4.0.1","multihashes":"~0.4.9"}},"0.4.2":{"name":"is-ipfs","dist":{"tarball":"https://registry.npmjs.org/is-ipfs/-/is-ipfs-0.4.2.tgz"},"scripts":{"test:node":"aegir test --target node","test:browser":"aegir test --target browser","test":"aegir test","lint":"aegir lint","release":"aegir release","release-minor":"aegir release --type minor","release-major":"aegir release --type major","build":"aegir build","coverage":"aegir coverage","coverage-publish":"aegir coverage --upload"},"dependencies":{"bs58":"4.0.1","cids":"0.5.3","multibase":"0.4.0","multihashes":"0.4.13"}},"0.4.6":{"name":"is-ipfs","dist":{"tarball":"https://registry.npmjs.org/is-ipfs/-/is-ipfs-0.4.6.tgz"},"scripts":{"test:node":"aegir test --target node","test:browser":"aegir test --target browser","test":"aegir test","lint":"aegir lint","release":"aegir release","release-minor":"aegir release --type minor","release-major":"aegir release --type major","build":"aegir build","coverage":"aegir coverage","coverage-publish":"aegir coverage --upload"},"dependencies":{"bs58":"4.0.1","cids":"0.5.4","multibase":"0.4.0","multihashes":"0.4.13"}},"0.4.7":{"name":"is-ipfs","dist":{"tarball":"https://registry.npmjs.org/is-ipfs/-/is-ipfs-0.4.7.tgz"},"scripts":{"test:node":"aegir test --target node","test:browser":"aegir test --target browser","test":"aegir test","lint":"aegir lint","release":"aegir release","release-minor":"aegir release --type minor","release-major":"aegir release --type major","build":"aegir build","coverage":"aegir coverage","coverage-publish":"aegir coverage --upload"},"dependencies":{"bs58":"4.0.1","cids":"~0.5.5","multibase":"~0.4.0","multihashes":"~0.4.13"}},"0.4.8":{"name":"is-ipfs","dist":{"tarball":"https://registry.npmjs.org/is-ipfs/-/is-ipfs-0.4.8.tgz"},"scripts":{"test:node":"aegir test --target node","test:browser":"aegir test --target browser","test":"aegir test","lint":"aegir lint","release":"aegir release","release-minor":"aegir release --type minor","release-major":"aegir release --type major","build":"aegir build","coverage":"aegir coverage","coverage-publish":"aegir coverage --upload"},"dependencies":{"bs58":"4.0.1","cids":"~0.5.6","multibase":"~0.6.0","multihashes":"~0.4.13"}},"0.5.1":{"name":"is-ipfs","dist":{"tarball":"https://registry.npmjs.org/is-ipfs/-/is-ipfs-0.5.1.tgz"},"scripts":{"test:node":"aegir test --target node","test:browser":"aegir test --target browser","test":"aegir test","lint":"aegir lint","release":"aegir release","release-minor":"aegir release --type minor","release-major":"aegir release --type major","build":"aegir build","coverage":"aegir coverage","coverage-publish":"aegir coverage --upload"},"dependencies":{"bs58":"4.0.1","cids":"~0.5.6","multibase":"~0.6.0","multihashes":"~0.4.13"}},"0.6.0":{"name":"is-ipfs","dist":{"tarball":"https://registry.npmjs.org/is-ipfs/-/is-ipfs-0.6.0.tgz"},"scripts":{"test:node":"aegir test --target node","test:browser":"aegir test --target browser","test":"aegir test","lint":"aegir lint","release":"aegir release","release-minor":"aegir release --type minor","release-major":"aegir release --type major","build":"aegir build","coverage":"aegir coverage","coverage-publish":"aegir coverage --upload"},"dependencies":{"bs58":"^4.0.1","cids":"~0.5.6","mafmt":"^v6.0.7","multiaddr":"^6.0.4","multibase":"~0.6.0","multihashes":"~0.4.13"}},"0.6.1":{"name":"is-ipfs","dist":{"tarball":"https://registry.npmjs.org/is-ipfs/-/is-ipfs-0.6.1.tgz"},"scripts":{"test:node":"aegir test --target node","test:browser":"aegir test --target browser","test":"aegir test","lint":"aegir lint","release":"aegir release","release-minor":"aegir release --type minor","release-major":"aegir release --type major","build":"aegir build","coverage":"aegir coverage","coverage-publish":"aegir coverage --upload"},"dependencies":{"bs58":"^4.0.1","cids":"~0.7.0","mafmt":"^6.0.7","multiaddr":"^6.0.4","multibase":"~0.6.0","multihashes":"~0.4.13"}},"0.6.2":{"name":"is-ipfs","dist":{"tarball":"https://registry.npmjs.org/is-ipfs/-/is-ipfs-0.6.2.tgz"},"scripts":{"test:node":"aegir test --target node","test:browser":"aegir test --target browser","test":"aegir test","lint":"aegir lint","release":"aegir release","release-minor":"aegir release --type minor","release-major":"aegir release --type major","build":"aegir build","coverage":"aegir coverage","coverage-publish":"aegir coverage --upload"},"dependencies":{"bs58":"^4.0.1","cids":"~0.7.0","mafmt":"^7.0.0","multiaddr":"^7.2.1","multibase":"~0.6.0","multihashes":"~0.4.13"}},"0.6.3":{"name":"is-ipfs","dist":{"tarball":"https://registry.npmjs.org/is-ipfs/-/is-ipfs-0.6.3.tgz"},"scripts":{"test:node":"aegir test --target node","test:browser":"aegir test --target browser","test":"aegir test","lint":"aegir lint","release":"aegir release","release-minor":"aegir release --type minor","release-major":"aegir release --type major","build":"aegir build","coverage":"aegir coverage","coverage-publish":"aegir coverage --upload"},"dependencies":{"bs58":"^4.0.1","cids":"~0.7.0","mafmt":"^7.0.0","multiaddr":"^7.2.1","multibase":"~0.6.0","multihashes":"~0.4.13"}},"1.0.0":{"name":"is-ipfs","dist":{"tarball":"https://registry.npmjs.org/is-ipfs/-/is-ipfs-1.0.0.tgz"},"scripts":{"test:node":"aegir test --target node","test:browser":"aegir test --target browser","test":"aegir test","lint":"aegir lint && aegir lint-package-json","release":"aegir release","release-minor":"aegir release --type minor","release-major":"aegir release --type major","build":"aegir build","coverage":"aegir coverage","coverage-publish":"aegir coverage --upload"},"dependencies":{"bs58":"^4.0.1","cids":"~0.8.0","iso-url":"~0.4.7","mafmt":"^7.1.0","multiaddr":"^7.4.3","multibase":"~0.7.0","multihashes":"~0.4.19"}},"1.0.3":{"name":"is-ipfs","dist":{"tarball":"https://registry.npmjs.org/is-ipfs/-/is-ipfs-1.0.3.tgz"},"scripts":{"test:node":"aegir test --target node","test:browser":"aegir test --target browser","test":"aegir test","lint":"aegir lint && aegir lint-package-json","release":"aegir release","release-minor":"aegir release --type minor","release-major":"aegir release --type major","build":"aegir build","coverage":"aegir coverage","coverage-publish":"aegir coverage --upload"},"dependencies":{"buffer":"^5.6.0","cids":"~0.8.0","iso-url":"~0.4.7","mafmt":"^7.1.0","multiaddr":"^7.4.3","multibase":"~0.7.0","multihashes":"~0.4.19"}},"2.0.0":{"name":"is-ipfs","dist":{"tarball":"https://registry.npmjs.org/is-ipfs/-/is-ipfs-2.0.0.tgz"},"scripts":{"test:node":"aegir test --target node","test:browser":"aegir test --target browser","test":"aegir test","lint":"aegir lint && aegir lint-package-json","release":"aegir release","release-minor":"aegir release --type minor","release-major":"aegir release --type major","build":"aegir build","coverage":"aegir coverage","coverage-publish":"aegir coverage --upload"},"dependencies":{"cids":"^1.0.0","iso-url":"~0.4.7","mafmt":"^8.0.0","multiaddr":"^8.0.0","multibase":"^3.0.0","multihashes":"^3.0.1","uint8arrays":"^1.1.0"}},"3.0.0":{"name":"is-ipfs","dist":{"tarball":"https://registry.npmjs.org/is-ipfs/-/is-ipfs-3.0.0.tgz"},"scripts":{"test:node":"aegir test --target node","test:browser":"aegir test --target browser","test":"aegir test","lint":"aegir lint && aegir lint-package-json","release":"aegir release","release-minor":"aegir release --type minor","release-major":"aegir release --type major","build":"aegir build","coverage":"aegir coverage","coverage-publish":"aegir coverage --upload"},"dependencies":{"cids":"^1.1.5","iso-url":"^1.0.0","mafmt":"^8.0.4","multiaddr":"^8.1.2","multibase":"^3.1.1","multihashes":"^3.1.2","uint8arrays":"^2.0.5"}},"4.0.0":{"name":"is-ipfs","dist":{"tarball":"https://registry.npmjs.org/is-ipfs/-/is-ipfs-4.0.0.tgz"},"scripts":{"prepare":"aegir build --no-bundle","test:node":"aegir test --target node","test:browser":"aegir test --target browser","test":"aegir test","prepublishOnly":"aegir build","lint":"aegir lint && aegir lint-package-json","release":"aegir release","release-minor":"aegir release --type minor","release-major":"aegir release --type major"},"dependencies":{"cids":"^1.1.6","iso-url":"^1.1.3","mafmt":"^8.0.4","multiaddr":"^8.1.2","multibase":"^4.0.2","multihashes":"^4.0.2","uint8arrays":"^2.1.3"}},"5.0.0":{"name":"is-ipfs","dist":{"tarball":"https://registry.npmjs.org/is-ipfs/-/is-ipfs-5.0.0.tgz"},"scripts":{"prepare":"aegir build --no-bundle","test:node":"aegir test --target node","test:browser":"aegir test --target browser","test":"aegir test","prepublishOnly":"aegir build","lint":"aegir lint && aegir lint-package-json","release":"aegir release","release-minor":"aegir release --type minor","release-major":"aegir release --type major"},"dependencies":{"cids":"^1.1.6","iso-url":"^1.1.3","mafmt":"^9.0.0","multiaddr":"^9.0.1","multibase":"^4.0.2","multihashes":"^4.0.2","uint8arrays":"^2.1.3"}},"6.0.0":{"name":"is-ipfs","dist":{"tarball":"https://registry.npmjs.org/is-ipfs/-/is-ipfs-6.0.0.tgz"},"scripts":{"prepare":"aegir build --no-bundle","test:node":"aegir test --target node","test:browser":"aegir test --target browser","test":"aegir test","prepublishOnly":"aegir build","lint":"aegir lint && aegir lint-package-json","release":"aegir release","release-minor":"aegir release --type minor","release-major":"aegir release --type major"},"dependencies":{"iso-url":"^1.1.3","mafmt":"^9.0.0","multiaddr":"^10.0.0","multiformats":"^9.0.0","uint8arrays":"^2.1.3"}},"6.0.1":{"name":"is-ipfs","dist":{"tarball":"https://registry.npmjs.org/is-ipfs/-/is-ipfs-6.0.1.tgz"},"scripts":{"prepare":"aegir build --no-bundle","test:node":"aegir test --target node","test:browser":"aegir test --target browser","test":"aegir test","prepublishOnly":"aegir build","lint":"aegir lint && aegir lint-package-json","release":"aegir release","release-minor":"aegir release --type minor","release-major":"aegir release --type major"},"dependencies":{"iso-url":"^1.1.3","mafmt":"^10.0.0","multiaddr":"^10.0.0","multiformats":"^9.0.0","uint8arrays":"^2.1.3"}},"6.0.2":{"name":"is-ipfs","dist":{"tarball":"https://registry.npmjs.org/is-ipfs/-/is-ipfs-6.0.2.tgz"},"scripts":{"prepare":"aegir build --no-bundle","test:node":"aegir test --target node","test:browser":"aegir test --target browser","test":"aegir test","prepublishOnly":"aegir build","lint":"aegir ts -p check && aegir lint-package-json && aegir lint","release":"aegir release","release-minor":"aegir release --type minor","release-major":"aegir release --type major"},"dependencies":{"iso-url":"^1.1.3","mafmt":"^10.0.0","multiaddr":"^10.0.0","multiformats":"^9.0.0","uint8arrays":"^3.0.0"}},"7.0.0":{"name":"is-ipfs","dist":{"tarball":"https://registry.npmjs.org/is-ipfs/-/is-ipfs-7.0.0.tgz"},"scripts":{"clean":"aegir clean","lint":"aegir lint","dep-check":"aegir dep-check","generate":"protons src/pb/peer.proto src/pb/tags.proto","build":"aegir build","test":"aegir test","test:chrome":"aegir test -t browser","test:chrome-webworker":"aegir test -t webworker","test:firefox":"aegir test -t browser -- --browser firefox","test:firefox-webworker":"aegir test -t webworker -- --browser firefox","test:node":"aegir test -t node","test:electron-main":"aegir test -t electron-main","release":"aegir release"},"dependencies":{"@multiformats/mafmt":"^11.0.3","@multiformats/multiaddr":"^11.0.0","iso-url":"^1.1.3","multiformats":"^9.0.0","uint8arrays":"^3.0.0"}},"7.0.1":{"name":"is-ipfs","dist":{"tarball":"https://registry.npmjs.org/is-ipfs/-/is-ipfs-7.0.1.tgz"},"scripts":{"clean":"aegir clean","lint":"aegir lint","dep-check":"aegir dep-check","generate":"protons src/pb/peer.proto src/pb/tags.proto","build":"aegir build","test":"aegir test","test:chrome":"aegir test -t browser","test:chrome-webworker":"aegir test -t webworker","test:firefox":"aegir test -t browser -- --browser firefox","test:firefox-webworker":"aegir test -t webworker -- --browser firefox","test:node":"aegir test -t node","test:electron-main":"aegir test -t electron-main","release":"aegir release"},"dependencies":{"@multiformats/mafmt":"^11.0.3","@multiformats/multiaddr":"^11.0.0","iso-url":"^1.1.3","multiformats":"^9.0.0","uint8arrays":"^3.0.0"}},"7.0.2":{"name":"is-ipfs","dist":{"tarball":"https://registry.npmjs.org/is-ipfs/-/is-ipfs-7.0.2.tgz"},"scripts":{"clean":"aegir clean","lint":"aegir lint","dep-check":"aegir dep-check","generate":"protons src/pb/peer.proto src/pb/tags.proto","build":"aegir build","test":"aegir test","test:chrome":"aegir test -t browser","test:chrome-webworker":"aegir test -t webworker","test:firefox":"aegir test -t browser -- --browser firefox","test:firefox-webworker":"aegir test -t webworker -- --browser firefox","test:node":"aegir test -t node","test:electron-main":"aegir test -t electron-main","release":"aegir release"},"dependencies":{"@multiformats/mafmt":"^11.0.3","@multiformats/multiaddr":"^11.0.0","iso-url":"^1.1.3","multiformats":"^9.0.0","uint8arrays":"^3.0.0"}},"7.0.3":{"name":"is-ipfs","dist":{"tarball":"https://registry.npmjs.org/is-ipfs/-/is-ipfs-7.0.3.tgz"},"scripts":{"clean":"aegir clean","lint":"aegir lint","dep-check":"aegir dep-check","generate":"protons src/pb/peer.proto src/pb/tags.proto","build":"aegir build","test":"aegir test","test:chrome":"aegir test -t browser","test:chrome-webworker":"aegir test -t webworker","test:firefox":"aegir test -t browser -- --browser firefox","test:firefox-webworker":"aegir test -t webworker -- --browser firefox","test:node":"aegir test -t node","test:electron-main":"aegir test -t electron-main","release":"aegir release"},"dependencies":{"@multiformats/mafmt":"^11.0.3","@multiformats/multiaddr":"^11.0.0","iso-url":"^1.1.3","multiformats":"^10.0.1","uint8arrays":"^4.0.2"}},"8.0.0":{"name":"is-ipfs","dist":{"tarball":"https://registry.npmjs.org/is-ipfs/-/is-ipfs-8.0.0.tgz"},"scripts":{"clean":"aegir clean","lint":"aegir lint","dep-check":"aegir dep-check","generate":"protons src/pb/peer.proto src/pb/tags.proto","build":"aegir build","test":"aegir test","test:chrome":"aegir test -t browser","test:chrome-webworker":"aegir test -t webworker","test:firefox":"aegir test -t browser -- --browser firefox","test:firefox-webworker":"aegir test -t webworker -- --browser firefox","test:node":"aegir test -t node","test:electron-main":"aegir test -t electron-main","release":"aegir release"},"dependencies":{"@multiformats/mafmt":"^11.0.3","@multiformats/multiaddr":"^11.0.0","iso-url":"^1.1.3","multiformats":"^11.0.0","uint8arrays":"^4.0.2"}},"8.0.1":{"name":"is-ipfs","dist":{"tarball":"https://registry.npmjs.org/is-ipfs/-/is-ipfs-8.0.1.tgz"},"scripts":{"clean":"aegir clean","lint":"aegir lint","dep-check":"aegir dep-check","generate":"protons src/pb/peer.proto src/pb/tags.proto","build":"aegir build","test":"aegir test","test:chrome":"aegir test -t browser","test:chrome-webworker":"aegir test -t webworker","test:firefox":"aegir test -t browser -- --browser firefox","test:firefox-webworker":"aegir test -t webworker -- --browser firefox","test:node":"aegir test -t node","test:electron-main":"aegir test -t electron-main","release":"aegir release","docs":"aegir docs"},"dependencies":{"@multiformats/mafmt":"^11.0.3","@multiformats/multiaddr":"^11.0.0","iso-url":"^1.1.3","multiformats":"^11.0.0","uint8arrays":"^4.0.2"}},"8.0.2":{"name":"is-ipfs","dist":{"tarball":"https://registry.npmjs.org/is-ipfs/-/is-ipfs-8.0.2.tgz"},"scripts":{"clean":"aegir clean","lint":"aegir lint","dep-check":"aegir dep-check","generate":"protons src/pb/peer.proto src/pb/tags.proto","build":"aegir build","test":"aegir test","test:chrome":"aegir test -t browser","test:chrome-webworker":"aegir test -t webworker","test:firefox":"aegir test -t browser -- --browser firefox","test:firefox-webworker":"aegir test -t webworker -- --browser firefox","test:node":"aegir test -t node","test:electron-main":"aegir test -t electron-main","release":"aegir release","docs":"aegir docs"},"dependencies":{"@multiformats/mafmt":"^12.1.6","@multiformats/multiaddr":"^12.1.14","iso-url":"^1.1.3","multiformats":"^11.0.0","uint8arrays":"^4.0.2"}},"8.0.3":{"name":"is-ipfs","dist":{"tarball":"https://registry.npmjs.org/is-ipfs/-/is-ipfs-8.0.3.tgz"},"scripts":{"build":"aegir build","test":"aegir test","test:node":"aegir test -t node --cov","test:chrome":"aegir test -t browser --cov","test:chrome-webworker":"aegir test -t webworker","test:firefox":"aegir test -t browser -- --browser firefox","test:firefox-webworker":"aegir test -t webworker -- --browser firefox","test:electron-main":"aegir test -t electron-main","lint":"aegir lint","dep-check":"aegir dep-check","release":"aegir release","docs":"aegir docs"},"dependencies":{"@multiformats/mafmt":"^12.1.6","@multiformats/multiaddr":"^12.1.14","iso-url":"^1.1.3","multiformats":"^11.0.0","uint8arrays":"^4.0.2"}},"8.0.4":{"name":"is-ipfs","dist":{"tarball":"https://registry.npmjs.org/is-ipfs/-/is-ipfs-8.0.4.tgz"},"scripts":{"build":"aegir build","test":"aegir test","test:node":"aegir test -t node --cov","test:chrome":"aegir test -t browser --cov","test:chrome-webworker":"aegir test -t webworker","test:firefox":"aegir test -t browser -- --browser firefox","test:firefox-webworker":"aegir test -t webworker -- --browser firefox","test:electron-main":"aegir test -t electron-main","lint":"aegir lint","dep-check":"aegir dep-check","release":"aegir release","docs":"aegir docs"},"dependencies":{"@multiformats/mafmt":"^12.1.6","@multiformats/multiaddr":"^12.1.14","iso-url":"^1.1.3","multiformats":"^13.0.1","uint8arrays":"^5.0.1"}}}},"etag":"W/\"495baab8904dcaf1e933b9c58fbf2b66\"","lastModified":"Tue, 06 Feb 2024 16:03:55 GMT"}
